aulas_publicacao_pacote/__init__.py
aulas_publicacao_pacote/modulo.py
aulas_publicacao_pacote-0.0.1.dist-info/LICENSE.txt
aulas_publicacao_pacote-0.0.1.dist-info/METADATA
aulas_publicacao_pacote-0.0.1.dist-info/WHEEL
aulas_publicacao_pacote-0.0.1.dist-info/top_level.txt
aulas_publicacao_pacote-0.0.1.dist-info/RECORD
