Metadata-Version: 2.1
Name: aulas-publicacao-pacote
Version: 0.0.1
Summary: Pacote python para exibir número de 1 a 9
Home-page: UNKNOWN
Author: Marcos Vinicius Vasconcelos Gomes
Author-email: marcossvinc@gmail.com
License: MIT License
Keywords: Pacote
Platform: UNKNOWN
License-File: LICENSE.txt
Requires-Dist: numpy
